{"_ts":[1564755426,1564842945,1565018644,1565062303,1565149109],"_r":{"breakdown":{"html":{"bytes":[1548,1549,1550,1551,1725],"requests":[3,3,3,3,3]},"js":{"bytes":[919971,928770,928388,832347,857856],"requests":[16,16,16,13,13]},"css":{"bytes":[19904,19904,19904,19904,20273],"requests":[3,3,3,3,3]},"image":{"bytes":[720870,720865,720870,49261,49261],"requests":[17,17,17,7,7]},"flash":{"bytes":[0,0,0,0,0],"requests":[0,0,0,0,0]},"font":{"bytes":[155560,155560,155560,124040,124040],"requests":[7,7,7,5,5]},"video":{"bytes":[0,0,0,0,0],"requests":[0,0,0,0,0]},"other":{"bytes":[39635,39643,39653,10814,11052],"requests":[22,22,22,15,16]}},"date":[1564755426,1564842945,1565018644,1565062303,1565149109],"domElements":[383,383,383,288.5,197],"domInteractive":[6463.5,6469,6489.5,6516,6523],"firstPaint":[6562.83000000295,6565.065000000101,6618.93750000305,6670.2000000005,6630.96249999945],"fullyLoaded":[21779.5,21543,21483,18969.5,15745.5],"id":["190802_JY_dc7709a351ea8bfb6ecd805086e37b2f","190803_BP_8b6a7de5b819a682f485a932cef58cd5","190805_99_155e802357ae91d1726819f6da5ff606","190806_4T_276ca19deed4bffc810cb4ff22ae8b38","190807_2V_cad594015270fc8cba128b1a131dbc66"],"loadTime":[19746,19313.5,18908,17621,15316],"render":[6600,6550,6600,6700,6650],"SpeedIndex":[12963.5,12568,12205,10528.5,8109],"TTFB":[1900,1892.5,1856,1920,1881.5],"videoFrames":[[{"_i":"ms_000000.jpg","_t":0,"_vc":0},{"_i":"ms_006600.jpg","_t":6600,"_vc":12},{"_i":"ms_006700.jpg","_t":6700,"_vc":13},{"_i":"ms_007000.jpg","_t":7000,"_vc":13},{"_i":"ms_007100.jpg","_t":7100,"_vc":13},{"_i":"ms_007200.jpg","_t":7200,"_vc":13},{"_i":"ms_007300.jpg","_t":7300,"_vc":13},{"_i":"ms_007400.jpg","_t":7400,"_vc":13},{"_i":"ms_007500.jpg","_t":7500,"_vc":13},{"_i":"ms_007600.jpg","_t":7600,"_vc":13},{"_i":"ms_007700.jpg","_t":7700,"_vc":13},{"_i":"ms_007800.jpg","_t":7800,"_vc":13},{"_i":"ms_007900.jpg","_t":7900,"_vc":13},{"_i":"ms_008000.jpg","_t":8000,"_vc":13},{"_i":"ms_008100.jpg","_t":8100,"_vc":13},{"_i":"ms_008200.jpg","_t":8200,"_vc":13},{"_i":"ms_008300.jpg","_t":8300,"_vc":13},{"_i":"ms_008400.jpg","_t":8400,"_vc":13},{"_i":"ms_008500.jpg","_t":8500,"_vc":13},{"_i":"ms_008600.jpg","_t":8600,"_vc":13},{"_i":"ms_008700.jpg","_t":8700,"_vc":13},{"_i":"ms_008800.jpg","_t":8800,"_vc":16},{"_i":"ms_008900.jpg","_t":8900,"_vc":16},{"_i":"ms_009000.jpg","_t":9000,"_vc":15},{"_i":"ms_009100.jpg","_t":9100,"_vc":15},{"_i":"ms_009200.jpg","_t":9200,"_vc":15},{"_i":"ms_009300.jpg","_t":9300,"_vc":18},{"_i":"ms_009400.jpg","_t":9400,"_vc":18},{"_i":"ms_009500.jpg","_t":9500,"_vc":18},{"_i":"ms_009600.jpg","_t":9600,"_vc":23},{"_i":"ms_009700.jpg","_t":9700,"_vc":29},{"_i":"ms_009800.jpg","_t":9800,"_vc":31},{"_i":"ms_009900.jpg","_t":9900,"_vc":31},{"_i":"ms_010000.jpg","_t":10000,"_vc":31},{"_i":"ms_010100.jpg","_t":10100,"_vc":28},{"_i":"ms_010200.jpg","_t":10200,"_vc":28},{"_i":"ms_010300.jpg","_t":10300,"_vc":28},{"_i":"ms_010400.jpg","_t":10400,"_vc":28},{"_i":"ms_010500.jpg","_t":10500,"_vc":28},{"_i":"ms_010600.jpg","_t":10600,"_vc":28},{"_i":"ms_010700.jpg","_t":10700,"_vc":28},{"_i":"ms_010800.jpg","_t":10800,"_vc":28},{"_i":"ms_010900.jpg","_t":10900,"_vc":28},{"_i":"ms_011000.jpg","_t":11000,"_vc":28},{"_i":"ms_011100.jpg","_t":11100,"_vc":28},{"_i":"ms_011200.jpg","_t":11200,"_vc":28},{"_i":"ms_011300.jpg","_t":11300,"_vc":28},{"_i":"ms_011400.jpg","_t":11400,"_vc":28},{"_i":"ms_011500.jpg","_t":11500,"_vc":28},{"_i":"ms_011600.jpg","_t":11600,"_vc":28},{"_i":"ms_012000.jpg","_t":12000,"_vc":28},{"_i":"ms_012500.jpg","_t":12500,"_vc":50},{"_i":"ms_013000.jpg","_t":13000,"_vc":50},{"_i":"ms_013500.jpg","_t":13500,"_vc":50},{"_i":"ms_014000.jpg","_t":14000,"_vc":52},{"_i":"ms_014500.jpg","_t":14500,"_vc":52},{"_i":"ms_015000.jpg","_t":15000,"_vc":52},{"_i":"ms_016100.jpg","_t":16100,"_vc":100}],[{"_i":"ms_000000.jpg","_t":0,"_vc":0},{"_i":"ms_006600.jpg","_t":6600,"_vc":12},{"_i":"ms_006700.jpg","_t":6700,"_vc":12},{"_i":"ms_007000.jpg","_t":7000,"_vc":13},{"_i":"ms_007100.jpg","_t":7100,"_vc":13},{"_i":"ms_007200.jpg","_t":7200,"_vc":13},{"_i":"ms_007300.jpg","_t":7300,"_vc":13},{"_i":"ms_007400.jpg","_t":7400,"_vc":13},{"_i":"ms_007500.jpg","_t":7500,"_vc":13},{"_i":"ms_007600.jpg","_t":7600,"_vc":13},{"_i":"ms_007700.jpg","_t":7700,"_vc":13},{"_i":"ms_007800.jpg","_t":7800,"_vc":13},{"_i":"ms_007900.jpg","_t":7900,"_vc":13},{"_i":"ms_008000.jpg","_t":8000,"_vc":13},{"_i":"ms_008100.jpg","_t":8100,"_vc":13},{"_i":"ms_008200.jpg","_t":8200,"_vc":13},{"_i":"ms_008300.jpg","_t":8300,"_vc":13},{"_i":"ms_008400.jpg","_t":8400,"_vc":13},{"_i":"ms_008500.jpg","_t":8500,"_vc":13},{"_i":"ms_008600.jpg","_t":8600,"_vc":13},{"_i":"ms_008700.jpg","_t":8700,"_vc":15},{"_i":"ms_008800.jpg","_t":8800,"_vc":15},{"_i":"ms_008900.jpg","_t":8900,"_vc":15},{"_i":"ms_009000.jpg","_t":9000,"_vc":15},{"_i":"ms_009100.jpg","_t":9100,"_vc":15},{"_i":"ms_009200.jpg","_t":9200,"_vc":15},{"_i":"ms_009300.jpg","_t":9300,"_vc":19},{"_i":"ms_009400.jpg","_t":9400,"_vc":19},{"_i":"ms_009500.jpg","_t":9500,"_vc":24},{"_i":"ms_009600.jpg","_t":9600,"_vc":24},{"_i":"ms_009700.jpg","_t":9700,"_vc":24},{"_i":"ms_009800.jpg","_t":9800,"_vc":25},{"_i":"ms_009900.jpg","_t":9900,"_vc":25},{"_i":"ms_010000.jpg","_t":10000,"_vc":25},{"_i":"ms_010100.jpg","_t":10100,"_vc":23},{"_i":"ms_010200.jpg","_t":10200,"_vc":23},{"_i":"ms_010300.jpg","_t":10300,"_vc":28},{"_i":"ms_010400.jpg","_t":10400,"_vc":28},{"_i":"ms_010500.jpg","_t":10500,"_vc":28},{"_i":"ms_010600.jpg","_t":10600,"_vc":28},{"_i":"ms_010700.jpg","_t":10700,"_vc":28},{"_i":"ms_010800.jpg","_t":10800,"_vc":28},{"_i":"ms_010900.jpg","_t":10900,"_vc":28},{"_i":"ms_011000.jpg","_t":11000,"_vc":28},{"_i":"ms_011100.jpg","_t":11100,"_vc":28},{"_i":"ms_011200.jpg","_t":11200,"_vc":28},{"_i":"ms_011300.jpg","_t":11300,"_vc":28},{"_i":"ms_011400.jpg","_t":11400,"_vc":28},{"_i":"ms_011500.jpg","_t":11500,"_vc":28},{"_i":"ms_011600.jpg","_t":11600,"_vc":28},{"_i":"ms_012000.jpg","_t":12000,"_vc":28},{"_i":"ms_012500.jpg","_t":12500,"_vc":50},{"_i":"ms_013000.jpg","_t":13000,"_vc":50},{"_i":"ms_013500.jpg","_t":13500,"_vc":50},{"_i":"ms_014000.jpg","_t":14000,"_vc":52},{"_i":"ms_014500.jpg","_t":14500,"_vc":52},{"_i":"ms_015000.jpg","_t":15000,"_vc":52},{"_i":"ms_016100.jpg","_t":16100,"_vc":100}],[{"_i":"ms_000000.jpg","_t":0,"_vc":0},{"_i":"ms_006600.jpg","_t":6600,"_vc":12},{"_i":"ms_006700.jpg","_t":6700,"_vc":13},{"_i":"ms_007100.jpg","_t":7100,"_vc":13},{"_i":"ms_007200.jpg","_t":7200,"_vc":13},{"_i":"ms_007300.jpg","_t":7300,"_vc":13},{"_i":"ms_007400.jpg","_t":7400,"_vc":12},{"_i":"ms_007500.jpg","_t":7500,"_vc":13},{"_i":"ms_007600.jpg","_t":7600,"_vc":13},{"_i":"ms_007700.jpg","_t":7700,"_vc":13},{"_i":"ms_007800.jpg","_t":7800,"_vc":13},{"_i":"ms_007900.jpg","_t":7900,"_vc":13},{"_i":"ms_008000.jpg","_t":8000,"_vc":13},{"_i":"ms_008100.jpg","_t":8100,"_vc":13},{"_i":"ms_008200.jpg","_t":8200,"_vc":13},{"_i":"ms_008300.jpg","_t":8300,"_vc":13},{"_i":"ms_008400.jpg","_t":8400,"_vc":13},{"_i":"ms_008500.jpg","_t":8500,"_vc":13},{"_i":"ms_008600.jpg","_t":8600,"_vc":13},{"_i":"ms_008700.jpg","_t":8700,"_vc":15},{"_i":"ms_008800.jpg","_t":8800,"_vc":15},{"_i":"ms_008900.jpg","_t":8900,"_vc":15},{"_i":"ms_009000.jpg","_t":9000,"_vc":15},{"_i":"ms_009100.jpg","_t":9100,"_vc":15},{"_i":"ms_009200.jpg","_t":9200,"_vc":15},{"_i":"ms_009300.jpg","_t":9300,"_vc":20},{"_i":"ms_009400.jpg","_t":9400,"_vc":20},{"_i":"ms_009500.jpg","_t":9500,"_vc":22},{"_i":"ms_009600.jpg","_t":9600,"_vc":24},{"_i":"ms_009700.jpg","_t":9700,"_vc":30},{"_i":"ms_009800.jpg","_t":9800,"_vc":31},{"_i":"ms_009900.jpg","_t":9900,"_vc":31},{"_i":"ms_010000.jpg","_t":10000,"_vc":30},{"_i":"ms_010100.jpg","_t":10100,"_vc":30},{"_i":"ms_010200.jpg","_t":10200,"_vc":28},{"_i":"ms_010300.jpg","_t":10300,"_vc":28},{"_i":"ms_010400.jpg","_t":10400,"_vc":28},{"_i":"ms_010500.jpg","_t":10500,"_vc":28},{"_i":"ms_010600.jpg","_t":10600,"_vc":28},{"_i":"ms_010700.jpg","_t":10700,"_vc":28},{"_i":"ms_010800.jpg","_t":10800,"_vc":28},{"_i":"ms_010900.jpg","_t":10900,"_vc":28},{"_i":"ms_011000.jpg","_t":11000,"_vc":28},{"_i":"ms_011100.jpg","_t":11100,"_vc":28},{"_i":"ms_011200.jpg","_t":11200,"_vc":28},{"_i":"ms_011300.jpg","_t":11300,"_vc":28},{"_i":"ms_011400.jpg","_t":11400,"_vc":28},{"_i":"ms_011500.jpg","_t":11500,"_vc":28},{"_i":"ms_011600.jpg","_t":11600,"_vc":28},{"_i":"ms_012000.jpg","_t":12000,"_vc":28},{"_i":"ms_012500.jpg","_t":12500,"_vc":50},{"_i":"ms_013000.jpg","_t":13000,"_vc":50},{"_i":"ms_013500.jpg","_t":13500,"_vc":52},{"_i":"ms_014000.jpg","_t":14000,"_vc":52},{"_i":"ms_014500.jpg","_t":14500,"_vc":52},{"_i":"ms_015000.jpg","_t":15000,"_vc":73},{"_i":"ms_015900.jpg","_t":15900,"_vc":100}],[{"_i":"ms_000000.jpg","_t":0,"_vc":0},{"_i":"ms_006600.jpg","_t":6600,"_vc":47},{"_i":"ms_007000.jpg","_t":7000,"_vc":47},{"_i":"ms_007100.jpg","_t":7100,"_vc":47},{"_i":"ms_007200.jpg","_t":7200,"_vc":47},{"_i":"ms_007300.jpg","_t":7300,"_vc":47},{"_i":"ms_007400.jpg","_t":7400,"_vc":47},{"_i":"ms_007500.jpg","_t":7500,"_vc":47},{"_i":"ms_007600.jpg","_t":7600,"_vc":47},{"_i":"ms_007700.jpg","_t":7700,"_vc":48},{"_i":"ms_007800.jpg","_t":7800,"_vc":48},{"_i":"ms_007900.jpg","_t":7900,"_vc":48},{"_i":"ms_008000.jpg","_t":8000,"_vc":47},{"_i":"ms_008100.jpg","_t":8100,"_vc":47},{"_i":"ms_008200.jpg","_t":8200,"_vc":47},{"_i":"ms_008300.jpg","_t":8300,"_vc":47},{"_i":"ms_008400.jpg","_t":8400,"_vc":47},{"_i":"ms_008500.jpg","_t":8500,"_vc":47},{"_i":"ms_008600.jpg","_t":8600,"_vc":47},{"_i":"ms_008700.jpg","_t":8700,"_vc":47},{"_i":"ms_008800.jpg","_t":8800,"_vc":47},{"_i":"ms_008900.jpg","_t":8900,"_vc":48},{"_i":"ms_009000.jpg","_t":9000,"_vc":48},{"_i":"ms_009100.jpg","_t":9100,"_vc":73},{"_i":"ms_009200.jpg","_t":9200,"_vc":72},{"_i":"ms_009300.jpg","_t":9300,"_vc":72},{"_i":"ms_009400.jpg","_t":9400,"_vc":72},{"_i":"ms_009500.jpg","_t":9500,"_vc":90},{"_i":"ms_009600.jpg","_t":9600,"_vc":90},{"_i":"ms_009700.jpg","_t":9700,"_vc":90},{"_i":"ms_009800.jpg","_t":9800,"_vc":90},{"_i":"ms_009900.jpg","_t":9900,"_vc":92},{"_i":"ms_010000.jpg","_t":10000,"_vc":99},{"_i":"ms_010100.jpg","_t":10100,"_vc":99},{"_i":"ms_010200.jpg","_t":10200,"_vc":99},{"_i":"ms_010300.jpg","_t":10300,"_vc":99},{"_i":"ms_010400.jpg","_t":10400,"_vc":99},{"_i":"ms_010500.jpg","_t":10500,"_vc":100},{"_i":"ms_010600.jpg","_t":10600,"_vc":99},{"_i":"ms_010700.jpg","_t":10700,"_vc":100},{"_i":"ms_010800.jpg","_t":10800,"_vc":100},{"_i":"ms_010900.jpg","_t":10900,"_vc":100},{"_i":"ms_011000.jpg","_t":11000,"_vc":100},{"_i":"ms_011100.jpg","_t":11100,"_vc":99},{"_i":"ms_011200.jpg","_t":11200,"_vc":99},{"_i":"ms_011300.jpg","_t":11300,"_vc":99},{"_i":"ms_011400.jpg","_t":11400,"_vc":99},{"_i":"ms_011500.jpg","_t":11500,"_vc":99},{"_i":"ms_011600.jpg","_t":11600,"_vc":99},{"_i":"ms_012000.jpg","_t":12000,"_vc":100},{"_i":"ms_012500.jpg","_t":12500,"_vc":99},{"_i":"ms_013000.jpg","_t":13000,"_vc":99},{"_i":"ms_013500.jpg","_t":13500,"_vc":99},{"_i":"ms_014000.jpg","_t":14000,"_vc":99},{"_i":"ms_014500.jpg","_t":14500,"_vc":100},{"_i":"ms_015000.jpg","_t":15000,"_vc":99},{"_i":"ms_015500.jpg","_t":15500,"_vc":100},{"_i":"ms_016000.jpg","_t":16000,"_vc":99},{"_i":"ms_016500.jpg","_t":16500,"_vc":100},{"_i":"ms_017000.jpg","_t":17000,"_vc":99},{"_i":"ms_017900.jpg","_t":17900,"_vc":100}],[{"_i":"ms_000000.jpg","_t":0,"_vc":0},{"_i":"ms_006900.jpg","_t":6900,"_vc":47},{"_i":"ms_007300.jpg","_t":7300,"_vc":47},{"_i":"ms_007400.jpg","_t":7400,"_vc":47},{"_i":"ms_007500.jpg","_t":7500,"_vc":47},{"_i":"ms_007600.jpg","_t":7600,"_vc":47},{"_i":"ms_007700.jpg","_t":7700,"_vc":47},{"_i":"ms_007800.jpg","_t":7800,"_vc":47},{"_i":"ms_007900.jpg","_t":7900,"_vc":47},{"_i":"ms_008000.jpg","_t":8000,"_vc":48},{"_i":"ms_008100.jpg","_t":8100,"_vc":48},{"_i":"ms_008200.jpg","_t":8200,"_vc":47},{"_i":"ms_008300.jpg","_t":8300,"_vc":47},{"_i":"ms_008400.jpg","_t":8400,"_vc":47},{"_i":"ms_008500.jpg","_t":8500,"_vc":47},{"_i":"ms_008600.jpg","_t":8600,"_vc":47},{"_i":"ms_008700.jpg","_t":8700,"_vc":47},{"_i":"ms_008800.jpg","_t":8800,"_vc":47},{"_i":"ms_008900.jpg","_t":8900,"_vc":47},{"_i":"ms_009000.jpg","_t":9000,"_vc":47},{"_i":"ms_009100.jpg","_t":9100,"_vc":48},{"_i":"ms_009200.jpg","_t":9200,"_vc":48},{"_i":"ms_009300.jpg","_t":9300,"_vc":86},{"_i":"ms_009400.jpg","_t":9400,"_vc":86},{"_i":"ms_009500.jpg","_t":9500,"_vc":86},{"_i":"ms_009600.jpg","_t":9600,"_vc":86},{"_i":"ms_009700.jpg","_t":9700,"_vc":86},{"_i":"ms_009800.jpg","_t":9800,"_vc":87},{"_i":"ms_009900.jpg","_t":9900,"_vc":87},{"_i":"ms_010000.jpg","_t":10000,"_vc":87},{"_i":"ms_010100.jpg","_t":10100,"_vc":95},{"_i":"ms_010200.jpg","_t":10200,"_vc":95},{"_i":"ms_010300.jpg","_t":10300,"_vc":95},{"_i":"ms_010400.jpg","_t":10400,"_vc":96},{"_i":"ms_010500.jpg","_t":10500,"_vc":99},{"_i":"ms_010600.jpg","_t":10600,"_vc":99},{"_i":"ms_010700.jpg","_t":10700,"_vc":99},{"_i":"ms_010800.jpg","_t":10800,"_vc":100},{"_i":"ms_010900.jpg","_t":10900,"_vc":100},{"_i":"ms_011000.jpg","_t":11000,"_vc":100},{"_i":"ms_011100.jpg","_t":11100,"_vc":100},{"_i":"ms_011200.jpg","_t":11200,"_vc":99},{"_i":"ms_011300.jpg","_t":11300,"_vc":100},{"_i":"ms_011400.jpg","_t":11400,"_vc":99},{"_i":"ms_011500.jpg","_t":11500,"_vc":99},{"_i":"ms_011600.jpg","_t":11600,"_vc":99},{"_i":"ms_011700.jpg","_t":11700,"_vc":99},{"_i":"ms_011800.jpg","_t":11800,"_vc":99},{"_i":"ms_011900.jpg","_t":11900,"_vc":99},{"_i":"ms_012000.jpg","_t":12000,"_vc":100},{"_i":"ms_012500.jpg","_t":12500,"_vc":100},{"_i":"ms_013000.jpg","_t":13000,"_vc":99},{"_i":"ms_013500.jpg","_t":13500,"_vc":100},{"_i":"ms_014000.jpg","_t":14000,"_vc":99},{"_i":"ms_014500.jpg","_t":14500,"_vc":100},{"_i":"ms_015000.jpg","_t":15000,"_vc":99},{"_i":"ms_015501.jpg","_t":15501,"_vc":99},{"_i":"ms_016000.jpg","_t":16000,"_vc":99},{"_i":"ms_016500.jpg","_t":16500,"_vc":99},{"_i":"ms_017000.jpg","_t":17000,"_vc":99},{"_i":"ms_018000.jpg","_t":18000,"_vc":99},{"_i":"ms_018100.jpg","_t":18100,"_vc":100}]],"visualComplete":[16150,15650,15350,13500,10300],"lighthouse":[23,23,23,23,23],"pagespeed":[73,73,73,73,73]}}