{"_ts":[1569980110],"_r":{"breakdown":{"html":{"bytes":[16000],"requests":[18]},"js":{"bytes":[1236416],"requests":[33]},"css":{"bytes":[19934],"requests":[3]},"image":{"bytes":[1206365],"requests":[49]},"flash":{"bytes":[0],"requests":[0]},"font":{"bytes":[155560],"requests":[7]},"video":{"bytes":[0],"requests":[0]},"other":{"bytes":[47743],"requests":[38]}},"date":[1569980110],"domElements":[508],"domInteractive":[3083.5],"firstPaint":[3732.6899999971],"fullyLoaded":[8787.5],"id":["191002_P8_05e9ea1c7b6d10ba30aa32714caee85a"],"loadTime":[7924],"render":[3750],"SpeedIndex":[5536],"TTFB":[1230],"videoFrames":[[{"_i":"ms_000000.jpg","_t":0,"_vc":0},{"_i":"ms_003700.jpg","_t":3700,"_vc":10},{"_i":"ms_004100.jpg","_t":4100,"_vc":10},{"_i":"ms_004200.jpg","_t":4200,"_vc":11},{"_i":"ms_004300.jpg","_t":4300,"_vc":11},{"_i":"ms_004400.jpg","_t":4400,"_vc":12},{"_i":"ms_004500.jpg","_t":4500,"_vc":12},{"_i":"ms_004600.jpg","_t":4600,"_vc":12},{"_i":"ms_004700.jpg","_t":4700,"_vc":12},{"_i":"ms_004800.jpg","_t":4800,"_vc":12},{"_i":"ms_004900.jpg","_t":4900,"_vc":12},{"_i":"ms_005000.jpg","_t":5000,"_vc":55},{"_i":"ms_005100.jpg","_t":5100,"_vc":55},{"_i":"ms_005200.jpg","_t":5200,"_vc":55},{"_i":"ms_005300.jpg","_t":5300,"_vc":55},{"_i":"ms_005400.jpg","_t":5400,"_vc":55},{"_i":"ms_005500.jpg","_t":5500,"_vc":55},{"_i":"ms_005600.jpg","_t":5600,"_vc":55},{"_i":"ms_005700.jpg","_t":5700,"_vc":55},{"_i":"ms_005800.jpg","_t":5800,"_vc":57},{"_i":"ms_005900.jpg","_t":5900,"_vc":57},{"_i":"ms_006000.jpg","_t":6000,"_vc":57},{"_i":"ms_006100.jpg","_t":6100,"_vc":75},{"_i":"ms_006200.jpg","_t":6200,"_vc":99},{"_i":"ms_006400.jpg","_t":6400,"_vc":100}]],"visualComplete":[6550],"lighthouse":[15],"pagespeed":[57]}}